aiozip/__init__.py
aiozip/exceptions.py
aiozip/structs.py
aiozip/uncompress.py
aiozip/zip_reader.py
aiozip-0.1.0.dist-info/METADATA
aiozip-0.1.0.dist-info/WHEEL
aiozip-0.1.0.dist-info/licenses/LICENSE
aiozip-0.1.0.dist-info/RECORD
