Metadata-Version: 2.4
Name: aiozip
Version: 0.1.0
Summary: A native asynchronous library for file decompression and archiving in Python.
Project-URL: Homepage, https://github.com/UoduodihsLab/aiozip
Project-URL: Bug Tracker, https://github.com/UoduodihsLab/aiozip/issues
Author-email: Uoduodihs <uoduodihs@gmail.com>
License: MIT License
License-File: LICENSE
Classifier: Development Status :: 3 - Alpha
Classifier: Framework :: AsyncIO
Classifier: Intended Audience :: Developers
Classifier: License :: OSI Approved :: MIT License
Classifier: Programming Language :: Python :: 3
Classifier: Programming Language :: Python :: 3.8
Classifier: Programming Language :: Python :: 3.9
Classifier: Programming Language :: Python :: 3.10
Classifier: Programming Language :: Python :: 3.11
Classifier: Programming Language :: Python :: 3.12
Classifier: Topic :: System :: Archiving
Classifier: Topic :: System :: Archiving :: Compression
Requires-Python: >=3.8
Requires-Dist: aiofiles>=23.0.0
Provides-Extra: test
Requires-Dist: pytest-asyncio>=0.21.0; extra == 'test'
Requires-Dist: pytest>=7.0.0; extra == 'test'
